odoo/addons/shopinvader_payment_condition/README.rst
odoo/addons/shopinvader_payment_condition/__init__.py
odoo/addons/shopinvader_payment_condition/__manifest__.py
odoo/addons/shopinvader_payment_condition/i18n/shopinvader_payment_condition.pot
odoo/addons/shopinvader_payment_condition/models/__init__.py
odoo/addons/shopinvader_payment_condition/models/shopinvader_payment.py
odoo/addons/shopinvader_payment_condition/readme/CONFIGURE.rst
odoo/addons/shopinvader_payment_condition/readme/CONTRIBUTORS.rst
odoo/addons/shopinvader_payment_condition/readme/DESCRIPTION.rst
odoo/addons/shopinvader_payment_condition/services/__init__.py
odoo/addons/shopinvader_payment_condition/services/abstract_payable_sale.py
odoo/addons/shopinvader_payment_condition/static/description/index.html
odoo/addons/shopinvader_payment_condition/tests/__init__.py
odoo/addons/shopinvader_payment_condition/tests/test_payment.py
odoo/addons/shopinvader_payment_condition/views/shopinvader_payment.xml
odoo14_addon_shopinvader_payment_condition-14.0.1.0.2.dist-info/METADATA
odoo14_addon_shopinvader_payment_condition-14.0.1.0.2.dist-info/WHEEL
odoo14_addon_shopinvader_payment_condition-14.0.1.0.2.dist-info/top_level.txt
odoo14_addon_shopinvader_payment_condition-14.0.1.0.2.dist-info/RECORD
