Metadata-Version: 2.1
Name: odoo14-addon-shopinvader-payment-condition
Version: 14.0.1.0.2
Summary: Filter available payment methods based on order conditions
Home-page: https://github.com/shopinvader/odoo-shopinvader-payment
Author: Camptocamp SA
License: AGPL-3
Platform: UNKNOWN
Classifier: Programming Language :: Python
Classifier: Framework :: Odoo
Classifier: Framework :: Odoo :: 14.0
Classifier: License :: OSI Approved :: GNU Affero General Public License v3
Requires-Python: >=3.6
Requires-Dist: odoo14-addon-shopinvader-payment
Requires-Dist: odoo (<14.1dev,>=14.0a)
